LICENSE
README.md
setup.cfg
setup.py
deep_phonemizer.egg-info/PKG-INFO
deep_phonemizer.egg-info/SOURCES.txt
deep_phonemizer.egg-info/dependency_links.txt
deep_phonemizer.egg-info/requires.txt
deep_phonemizer.egg-info/top_level.txt
dp/__init__.py
dp/phonemizer.py
dp/preprocess.py
dp/result.py
dp/train.py
dp/configs/__init__.py
dp/configs/autoreg_config.yaml
dp/configs/forward_config.yaml
dp/configs/forward_config_espeak_enrp.yaml
dp/configs/forward_config_espeak_enuk.yaml
dp/model/__init__.py
dp/model/model.py
dp/model/predictor.py
dp/model/utils.py
dp/preprocessing/__init__.py
dp/preprocessing/text.py
dp/preprocessing/utils.py
dp/training/__init__.py
dp/training/dataset.py
dp/training/decorators.py
dp/training/evaluation.py
dp/training/losses.py
dp/training/metrics.py
dp/training/trainer.py
dp/utils/__init__.py
dp/utils/io.py
dp/utils/logging.py
tests/test_autoreg_training.py
tests/test_dataset.py
tests/test_decorators.py
tests/test_evaluation.py
tests/test_forward_training.py
tests/test_language_tokenizer.py
tests/test_metrics.py
tests/test_phonemizer.py
tests/test_predictor.py
tests/test_preprocess.py
tests/test_preprocessor.py
tests/test_sequence_tokenizer.py